constella/__init__.py
constella/clustering/__init__.py
constella/clustering/kmeans.py
constella/config/__init__.py
constella/config/schemas.py
constella/data/__init__.py
constella/data/models.py
constella/data/results.py
constella/embeddings/__init__.py
constella/embeddings/adapters.py
constella/embeddings/base.py
constella/labeling/__init__.py
constella/labeling/auto_label.py
constella/labeling/prompts.py
constella/labeling/providers.py
constella/labeling/response_parsing.py
constella/labeling/selection.py
constella/pipelines/__init__.py
constella/pipelines/workflow.py
constella/visualization/__init__.py
constella/visualization/artifacts.py
constella/visualization/html_templates.py
constella/visualization/umap.py
constella/visualization/umap_hover.html
constella-0.1.0.dist-info/METADATA
constella-0.1.0.dist-info/WHEEL
constella-0.1.0.dist-info/top_level.txt
constella-0.1.0.dist-info/RECORD
