Metadata-Version: 2.4
Name: constella
Version: 0.1.0
Summary: Auto-grouping and auto-labeling for text corpora
Author: Constella Contributors
License: MIT
Requires-Python: >=3.11
Requires-Dist: numpy>=2.3.3
Requires-Dist: scikit-learn>=1.3
Requires-Dist: matplotlib>=3.7
Requires-Dist: umap-learn>=0.5.5
Requires-Dist: numba>=0.62.1
Requires-Dist: streamlit>=1.37
Requires-Dist: litellm>=1.79
Requires-Dist: psycopg>=3.2.12
Provides-Extra: test
Requires-Dist: pytest>=7.4; extra == "test"
Requires-Dist: pytest-mock>=3.10; extra == "test"
